webcampicture/__init__.py
webcampicture/admin.py
webcampicture/apps.py
webcampicture/constants.py
webcampicture/fields.py
webcampicture/forms.py
webcampicture/migrations/__init__.py
webcampicture/models.py
webcampicture/static/webcampicture/css/webcampicture.css
webcampicture/static/webcampicture/js/webcampicture.js
webcampicture/templates/webcampicture/webcampicture.html
webcampicture/tests.py
webcampicture/views.py
webcampicture/widgets.py
django_webcampicture-0.1.9.dist-info/LICENSE
django_webcampicture-0.1.9.dist-info/WHEEL
django_webcampicture-0.1.9.dist-info/METADATA
django_webcampicture-0.1.9.dist-info/RECORD
