Metadata-Version: 2.1
Name: django-webcampicture
Version: 0.1.9
Summary: A Django app to provide a WebcamPictureField, derived from FileField.
Home-page: https://github.com/rnetonet/django-webcampicture
License: MIT
Author: rnetonet
Author-email: rneto@rneto.net
Requires-Python: >=3.6,<4.0
Classifier: Framework :: Django
Classifier: Framework :: Django :: 1.11
Classifier: Framework :: Django :: 2.0
Classifier: Framework :: Django :: 3.0
Classifier: Intended Audience :: Developers
Classifier: License :: OSI Approved :: MIT License
Classifier: Operating System :: OS Independent
Classifier: Programming Language :: Python
Classifier: Programming Language :: Python :: 3
Classifier: Programming Language :: Python :: 3 :: Only
Classifier: Programming Language :: Python :: 3.6
Classifier: Programming Language :: Python :: 3.7
Classifier: Programming Language :: Python :: 3.8
Classifier: Programming Language :: Python :: 3.9
Project-URL: Repository, https://github.com/rnetonet/django-webcampicture
